{
  "cached_count": 0,
  "candidates_per_second": 0.241563,
  "class_counts": {
    "solver_bottleneck": 240
  },
  "completed_count": 240,
  "elapsed_seconds": 993.53,
  "eta_seconds": 0.0,
  "pending_count": 0,
  "scanner_version": "bloch_path_a_stepwise_v5",
  "selected_count": 240,
  "slowest_candidates": [
    {
      "class": "solver_bottleneck",
      "elapsed_seconds": 22.36,
      "name": "path_a_projector_free_p6_c12340_s34443",
      "ranks": []
    },
    {
      "class": "solver_bottleneck",
      "elapsed_seconds": 22.295,
      "name": "path_a_projector_free_p6_c30142_s43344",
      "ranks": []
    },
    {
      "class": "solver_bottleneck",
      "elapsed_seconds": 22.242,
      "name": "path_a_projector_free_p6_c24103_s43344",
      "ranks": []
    },
    {
      "class": "solver_bottleneck",
      "elapsed_seconds": 22.163,
      "name": "path_a_projector_free_p6_c30142_s34344",
      "ranks": []
    },
    {
      "class": "solver_bottleneck",
      "elapsed_seconds": 22.149,
      "name": "path_a_projector_free_p6_c24103_s34344",
      "ranks": []
    }
  ],
  "stage_average_seconds": {
    "bloch_layer": 1e-05,
    "bloch_samples": 0.098771,
    "center_basis": 4.132643,
    "closure": 7.632907,
    "generator_reduction": 1.57825,
    "laurent": 0.001798,
    "layer": 0.128923
  },
  "total_candidate_space": 2400
}